fastApi_jwtAuth/__init__.py
fastApi_jwtAuth/authentication.py
fastApi_jwtAuth-0.0.1.dist-info/LICENSE
fastApi_jwtAuth-0.0.1.dist-info/METADATA
fastApi_jwtAuth-0.0.1.dist-info/WHEEL
fastApi_jwtAuth-0.0.1.dist-info/top_level.txt
fastApi_jwtAuth-0.0.1.dist-info/RECORD
