Metadata-Version: 2.1
Name: fastApi-jwtAuth
Version: 0.0.1
Summary: JWT authentication package for FastAPI framework.
Home-page: http://packages.python.org/an_example_pypi_project
Author: MohammadAmin Parvanian
Author-email: amin_prvn@outlook.com
License: Apache License 2.0
Platform: UNKNOWN
Classifier: Development Status :: 3 - Alpha
Classifier: Topic :: Utilities
Classifier: License :: OSI Approved :: BSD License
Requires-Python: >=3
